convert_to_quant/__init__.py
convert_to_quant/calibrate_activation_scales.py
convert_to_quant/constants.py
convert_to_quant/convert_to_quant.py
convert_to_quant/pinned_transfer.py
convert_to_quant/cli/__init__.py
convert_to_quant/cli/argument_parser.py
convert_to_quant/cli/main.py
convert_to_quant/comfy/__init__.py
convert_to_quant/comfy/float.py
convert_to_quant/comfy/int8_kernels.py
convert_to_quant/comfy/quant_ops.py
convert_to_quant/config/__init__.py
convert_to_quant/config/layer_config.py
convert_to_quant/converters/__init__.py
convert_to_quant/converters/base_converter.py
convert_to_quant/converters/learned_mxfp8.py
convert_to_quant/converters/learned_nvfp4.py
convert_to_quant/converters/learned_rounding.py
convert_to_quant/converters/mxfp8_converter.py
convert_to_quant/converters/nvfp4_converter.py
convert_to_quant/formats/__init__.py
convert_to_quant/formats/format_migration.py
convert_to_quant/formats/fp8_conversion.py
convert_to_quant/formats/hybrid_mxfp8_conversion.py
convert_to_quant/formats/int8_conversion.py
convert_to_quant/formats/legacy_utils.py
convert_to_quant/formats/mxfp8_conversion.py
convert_to_quant/formats/nvfp4_conversion.py
convert_to_quant/utils/__init__.py
convert_to_quant/utils/comfy_quant.py
convert_to_quant/utils/float_utils.py
convert_to_quant/utils/logging.py
convert_to_quant/utils/memory_efficient_loader.py
convert_to_quant/utils/tensor_utils.py
convert_to_quant-1.1.0.dist-info/METADATA
convert_to_quant-1.1.0.dist-info/WHEEL
convert_to_quant-1.1.0.dist-info/entry_points.txt
convert_to_quant-1.1.0.dist-info/top_level.txt
convert_to_quant-1.1.0.dist-info/RECORD
