Metadata-Version: 2.4
Name: convert_to_quant
Version: 1.1.0
Summary: Convert safetensors weights to quantized formats (FP8, INT8) with learned rounding optimization
License: MIT
Project-URL: Repository, https://github.com/silveroxides/convert_to_quant
Keywords: quantization,fp8,int8,machine-learning,pytorch,comfyui
Classifier: Development Status :: 4 - Beta
Classifier: Intended Audience :: Developers
Classifier: Intended Audience :: Science/Research
Classifier: License :: OSI Approved :: MIT License
Classifier: Programming Language :: Python :: 3
Classifier: Programming Language :: Python :: 3.10
Classifier: Programming Language :: Python :: 3.11
Classifier: Programming Language :: Python :: 3.12
Classifier: Topic :: Scientific/Engineering :: Artificial Intelligence
Requires-Python: >=3.10
Provides-Extra: triton
Requires-Dist: triton>=2.1.0; extra == "triton"
Provides-Extra: triton-windows
Requires-Dist: triton-windows<3.6,>=3.3; extra == "triton-windows"
Provides-Extra: dev
Requires-Dist: pytest; extra == "dev"
Requires-Dist: ruff; extra == "dev"
